gpxt/__init__.py
gpxt/__main__.py
gpxt/tools/__init__.py
gpxt/tools/_tool_descriptor.py
gpxt/tools/dummy.py
gpxt-0.0.1.dist-info/licenses/LICENSE
gpxt-0.0.1.dist-info/METADATA
gpxt-0.0.1.dist-info/WHEEL
gpxt-0.0.1.dist-info/entry_points.txt
gpxt-0.0.1.dist-info/top_level.txt
gpxt-0.0.1.dist-info/RECORD
