Metadata-Version: 2.4
Name: gpxt
Version: 0.0.1
Summary: GPX Tools - A collection of tools to work with GPX files.
Author-email: Neri <neri@n3r1.com>
Project-URL: Homepage, https://github.com/neri14/gpxt
Project-URL: Repository, https://github.com/neri14/gpxt
Project-URL: Issues, https://github.com/neri14/gpxt/issues
Classifier: Development Status :: 2 - Pre-Alpha
Classifier: Intended Audience :: End Users/Desktop
Classifier: Intended Audience :: Other Audience
Classifier: Programming Language :: Python :: 3
Classifier: Programming Language :: Python :: 3.12
Classifier: Programming Language :: Python :: 3.13
Requires-Python: >=3.12
License-File: LICENSE
Provides-Extra: dev
Requires-Dist: pytest; extra == "dev"
Requires-Dist: pytest-cov; extra == "dev"
Requires-Dist: mypy; extra == "dev"
Dynamic: license-file
